{
    "Ar36": {
        "error": 0.00062343921454027968, 
        "fit": "Parabolic", 
        "value": 0.00065713673211158902
    }, 
    "Ar37": {
        "error": 0.046406079108340034, 
        "fit": "linear", 
        "value": -0.017384347011825941
    }, 
    "Ar38": {
        "error": 0.019716735941844782, 
        "fit": "linear", 
        "value": -0.018391793753116854
    }, 
    "Ar39": {
        "error": 0.045893419297681509, 
        "fit": "Parabolic", 
        "value": -0.20600813517605732
    }, 
    "Ar40": {
        "error": 0.045136545248785659, 
        "fit": "Parabolic", 
        "value": 0.078217920882185224
    }, 
    "Ar41": {
        "error": 0.11050612435973454, 
        "fit": "linear", 
        "value": 0.10121550328825302
    }
}