{
    "AX": {
        "error": 0.04599957759739845, 
        "fit": "average", 
        "value": 0.028022646715247332
    }, 
    "CDD": {
        "error": 4.207586205708917e-05, 
        "fit": "average", 
        "value": 1.0842278667648013e-05
    }, 
    "H1": {
        "error": 0.04027322128093163, 
        "fit": "average", 
        "value": -0.046092035633449935
    }, 
    "H2": {
        "error": 0.0360090000341284, 
        "fit": "average", 
        "value": 0.08160626136841961
    }, 
    "L1": {
        "error": 0.050800160038840005, 
        "fit": "average", 
        "value": 0.14214122932144377
    }, 
    "L2": {
        "error": 0.01736355507536724, 
        "fit": "average", 
        "value": 0.00026350605665952543
    }
}