{
    "Ar36": {
        "error": 0.0010997432330153826, 
        "fit": "Parabolic", 
        "value": 0.0067900898538140637
    }, 
    "Ar37": {
        "error": 0.019210609273117404, 
        "fit": "linear", 
        "value": 0.29227986596600836
    }, 
    "Ar38": {
        "error": 0.045947641172587268, 
        "fit": "linear", 
        "value": 0.16999429310111011
    }, 
    "Ar39": {
        "error": 0.052499696439142929, 
        "fit": "Parabolic", 
        "value": 1.6792629788292579
    }, 
    "Ar40": {
        "error": 0.041087042445134093, 
        "fit": "Parabolic", 
        "value": 2.214078208724386
    }, 
    "Ar41": {
        "error": 0.047627974869478257, 
        "fit": "linear", 
        "value": 0.073654521857945118
    }
}