{
    "Ar36": {
        "error": 0.0013755727814230368, 
        "fit": "Parabolic", 
        "value": 0.013427353716700348
    }, 
    "Ar37": {
        "error": 0.02116673657921957, 
        "fit": "linear", 
        "value": 0.91035437790690232
    }, 
    "Ar38": {
        "error": 0.04594492202534177, 
        "fit": "linear", 
        "value": 0.16862403017609962
    }, 
    "Ar39": {
        "error": 0.053751374159246773, 
        "fit": "Parabolic", 
        "value": 1.5565149051814418
    }, 
    "Ar40": {
        "error": 0.044059557722905936, 
        "fit": "Parabolic", 
        "value": 2.6260214874191927
    }, 
    "Ar41": {
        "error": 0.048947937690076555, 
        "fit": "linear", 
        "value": 0.084978024778207234
    }
}